package com.d0klabs.cryptowalt.data;

public interface Opcode {
    int opc_nop = 0;
    int opc_aconst_null = 1;
    int opc_iconst_m1 = 2;
    int opc_iconst_0 = 3;
    int opc_iconst_1 = 4;
    int opc_iconst_2 = 5;
    int opc_iconst_3 = 6;
    int opc_iconst_4 = 7;
    int opc_iconst_5 = 8;
    int opc_lconst_0 = 9;
    int opc_lconst_1 = 10;
    int opc_fconst_0 = 11;
    int opc_fconst_1 = 12;
    int opc_fconst_2 = 13;
    int opc_dconst_0 = 14;
    int opc_dconst_1 = 15;
    int opc_bipush = 16;
    int opc_sipush = 17;
    int opc_ldc = 18;
    int opc_ldc_w = 19;
    int opc_ldc2_w = 20;
    int opc_iload = 21;
    int opc_lload = 22;
    int opc_fload = 23;
    int opc_dload = 24;
    int opc_aload = 25;
    int opc_iload_0 = 26;
    int opc_iload_1 = 27;
    int opc_iload_2 = 28;
    int opc_iload_3 = 29;
    int opc_lload_0 = 30;
    int opc_lload_1 = 31;
    int opc_lload_2 = 32;
    int opc_lload_3 = 33;
    int opc_fload_0 = 34;
    int opc_fload_1 = 35;
    int opc_fload_2 = 36;
    int opc_fload_3 = 37;
    int opc_dload_0 = 38;
    int opc_dload_1 = 39;
    int opc_dload_2 = 40;
    int opc_dload_3 = 41;
    int opc_aload_0 = 42;
    int opc_aload_1 = 43;
    int opc_aload_2 = 44;
    int opc_aload_3 = 45;
    int opc_iaload = 46;
    int opc_laload = 47;
    int opc_faload = 48;
    int opc_daload = 49;
    int opc_aaload = 50;
    int opc_baload = 51;
    int opc_caload = 52;
    int opc_saload = 53;
    int opc_istore = 54;
    int opc_lstore = 55;
    int opc_fstore = 56;
    int opc_dstore = 57;
    int opc_astore = 58;
    int opc_istore_0 = 59;
    int opc_istore_1 = 60;
    int opc_istore_2 = 61;
    int opc_istore_3 = 62;
    int opc_lstore_0 = 63;
    int opc_lstore_1 = 64;
    int opc_lstore_2 = 65;
    int opc_lstore_3 = 66;
    int opc_fstore_0 = 67;
    int opc_fstore_1 = 68;
    int opc_fstore_2 = 69;
    int opc_fstore_3 = 70;
    int opc_dstore_0 = 71;
    int opc_dstore_1 = 72;
    int opc_dstore_2 = 73;
    int opc_dstore_3 = 74;
    int opc_astore_0 = 75;
    int opc_astore_1 = 76;
    int opc_astore_2 = 77;
    int opc_astore_3 = 78;
    int opc_iastore = 79;
    int opc_lastore = 80;
    int opc_fastore = 81;
    int opc_dastore = 82;
    int opc_aastore = 83;
    int opc_bastore = 84;
    int opc_castore = 85;
    int opc_sastore = 86;
    int opc_pop = 87;
    int opc_pop2 = 88;
    int opc_dup = 89;
    int opc_dup_x1 = 90;
    int opc_dup_x2 = 91;
    int opc_dup2 = 92;
    int opc_dup2_x1 = 93;
    int opc_dup2_x2 = 94;
    int opc_swap = 95;
    int opc_iadd = 96;
    int opc_ladd = 97;
    int opc_fadd = 98;
    int opc_dadd = 99;
    int opc_isub = 100;
    int opc_lsub = 101;
    int opc_fsub = 102;
    int opc_dsub = 103;
    int opc_imul = 104;
    int opc_lmul = 105;
    int opc_fmul = 106;
    int opc_dmul = 107;
    int opc_idiv = 108;
    int opc_ldiv = 109;
    int opc_fdiv = 110;
    int opc_ddiv = 111;
    int opc_irem = 112;
    int opc_lrem = 113;
    int opc_frem = 114;
    int opc_drem = 115;
    int opc_ineg = 116;
    int opc_lneg = 117;
    int opc_fneg = 118;
    int opc_dneg = 119;
    int opc_ishl = 120;
    int opc_lshl = 121;
    int opc_ishr = 122;
    int opc_lshr = 123;
    int opc_iushr = 124;
    int opc_lushr = 125;
    int opc_iand = 126;
    int opc_land = 127;
    int opc_ior = 128;
    int opc_lor = 129;
    int opc_ixor = 130;
    int opc_lxor = 131;
    int opc_iinc = 132;
    int opc_i2l = 133;
    int opc_i2f = 134;
    int opc_i2d = 135;
    int opc_l2i = 136;
    int opc_l2f = 137;
    int opc_l2d = 138;
    int opc_f2i = 139;
    int opc_f2l = 140;
    int opc_f2d = 141;
    int opc_d2i = 142;
    int opc_d2l = 143;
    int opc_d2f = 144;
    int opc_i2b = 145;
    int opc_i2c = 146;
    int opc_i2s = 147;
    int opc_lcmp = 148;
    int opc_fcmpl = 149;
    int opc_fcmpg = 150;
    int opc_dcmpl = 151;
    int opc_dcmpg = 152;
    int opc_ifeq = 153;
    int opc_ifne = 154;
    int opc_iflt = 155;
    int opc_ifge = 156;
    int opc_ifgt = 157;
    int opc_ifle = 158;
    int opc_if_icmpeq = 159;
    int opc_if_icmpne = 160;
    int opc_if_icmplt = 161;
    int opc_if_icmpge = 162;
    int opc_if_icmpgt = 163;
    int opc_if_icmple = 164;
    int opc_if_acmpeq = 165;
    int opc_if_acmpne = 166;
    int opc_goto = 167;
    int opc_jsr = 168;
    int opc_ret = 169;
    int opc_tableswitch = 170;
    int opc_lookupswitch = 171;
    int opc_ireturn = 172;
    int opc_lreturn = 173;
    int opc_freturn = 174;
    int opc_dreturn = 175;
    int opc_areturn = 176;
    int opc_return = 177;
    int opc_getstatic = 178;
    int opc_putstatic = 179;
    int opc_getfield = 180;
    int opc_putfield = 181;
    int opc_invokevirtual = 182;
    int opc_invokespecial = 183;
    int opc_invokestatic = 184;
    int opc_invokeinterface = 185;
    int opc_xxxunusedxxx = 186;
    int opc_new = 187;
    int opc_newarray = 188;
    int opc_anewarray = 189;
    int opc_arraylength = 190;
    int opc_athrow = 191;
    int opc_checkcast = 192;
    int opc_instanceof = 193;
    int opc_monitorenter = 194;
    int opc_monitorexit = 195;
    int opc_wide = 196;
    int opc_multianewarray = 197;
    int opc_ifnull = 198;
    int opc_ifnonnull = 199;
    int opc_goto_w = 200;
    int opc_jsr_w = 201;
    int opc_breakpoint = 202;
    int opc_rc = 237;
    int opc_aupdate = 238;
    int opc_supdate = 239;
    int opc_aswizzle = 240;
    int opc_aswrange = 241;
    int opc_putfield_nowb = 204;
    int opc_putstatic_nowb = 205;
    int opcx_nop = 0;
    int opcx_ldc = 18;
    int opcx_iload = 21;
    int opcx_lload = 22;
    int opcx_fload = 23;
    int opcx_dload = 24;
    int opcx_aload = 25;
    int opcx_iaload = 46;
    int opcx_laload = 47;
    int opcx_faload = 48;
    int opcx_daload = 49;
    int opcx_aaload = 50;
    int opcx_baload = 51;
    int opcx_caload = 52;
    int opcx_saload = 53;
    int opcx_istore = 54;
    int opcx_lstore = 55;
    int opcx_fstore = 56;
    int opcx_dstore = 57;
    int opcx_astore = 58;
    int opcx_iastore = 79;
    int opcx_lastore = 80;
    int opcx_fastore = 81;
    int opcx_dastore = 82;
    int opcx_aastore = 83;
    int opcx_bastore = 84;
    int opcx_castore = 85;
    int opcx_sastore = 86;
    int opcx_pop = 87;
    int opcx_pop2 = 88;
    int opcx_dup = 89;
    int opcx_dup_x1 = 90;
    int opcx_dup_x2 = 91;
    int opcx_dup2 = 92;
    int opcx_dup2_x1 = 93;
    int opcx_dup2_x2 = 94;
    int opcx_swap = 95;
    int opcx_iadd = 96;
    int opcx_ladd = 97;
    int opcx_fadd = 98;
    int opcx_dadd = 99;
    int opcx_isub = 100;
    int opcx_lsub = 101;
    int opcx_fsub = 102;
    int opcx_dsub = 103;
    int opcx_imul = 104;
    int opcx_lmul = 105;
    int opcx_fmul = 106;
    int opcx_dmul = 107;
    int opcx_idiv = 108;
    int opcx_ldiv = 109;
    int opcx_fdiv = 110;
    int opcx_ddiv = 111;
    int opcx_irem = 112;
    int opcx_lrem = 113;
    int opcx_frem = 114;
    int opcx_drem = 115;
    int opcx_ineg = 116;
    int opcx_lneg = 117;
    int opcx_fneg = 118;
    int opcx_dneg = 119;
    int opcx_ishl = 120;
    int opcx_lshl = 121;
    int opcx_ishr = 122;
    int opcx_lshr = 123;
    int opcx_iushr = 124;
    int opcx_lushr = 125;
    int opcx_iand = 126;
    int opcx_land = 127;
    int opcx_ior = 128;
    int opcx_lor = 129;
    int opcx_ixor = 130;
    int opcx_lxor = 131;
    int opcx_iinc = 132;
    int opcx_i2l = 133;
    int opcx_i2f = 134;
    int opcx_i2d = 135;
    int opcx_l2i = 136;
    int opcx_l2f = 137;
    int opcx_l2d = 138;
    int opcx_f2i = 139;
    int opcx_f2l = 140;
    int opcx_f2d = 141;
    int opcx_d2i = 142;
    int opcx_d2l = 143;
    int opcx_d2f = 144;
    int opcx_i2b = 145;
    int opcx_i2c = 146;
    int opcx_i2s = 147;
    int opcx_lcmp = 148;
    int opcx_fcmpl = 149;
    int opcx_fcmpg = 150;
    int opcx_dcmpl = 151;
    int opcx_dcmpg = 152;
    int opcx_ifeq = 153;
    int opcx_ifne = 154;
    int opcx_iflt = 155;
    int opcx_ifge = 156;
    int opcx_ifgt = 157;
    int opcx_ifle = 158;
    int opcx_if_icmpeq = 159;
    int opcx_if_icmpne = 160;
    int opcx_if_icmplt = 161;
    int opcx_if_icmpge = 162;
    int opcx_if_icmpgt = 163;
    int opcx_if_icmple = 164;
    int opcx_if_acmpeq = 165;
    int opcx_if_acmpne = 166;
    int opcx_goto = 167;
    int opcx_jsr = 168;
    int opcx_ret = 169;
    int opcx_switch = 170;
    int opcx_ireturn = 172;
    int opcx_lreturn = 173;
    int opcx_freturn = 174;
    int opcx_dreturn = 175;
    int opcx_areturn = 176;
    int opcx_return = 177;
    int opcx_getstatic = 178;
    int opcx_putstatic = 179;
    int opcx_getfield = 180;
    int opcx_putfield = 181;
    int opcx_invokevirtual = 182;
    int opcx_invokespecial = 183;
    int opcx_invokestatic = 184;
    int opcx_invokeinterface = 185;
    int opcx_new = 187;
    int opcx_newarray = 188;
    int opcx_arraylength = 190;
    int opcx_athrow = 191;
    int opcx_checkcast = 192;
    int opcx_instanceof = 193;
    int opcx_monitorenter = 194;
    int opcx_monitorexit = 195;
    int opcx_multianewarray = 197;
    int opcx_ifnull = 198;
    int opcx_ifnonnull = 199;
    int opcx_aupdate = 238;
    int opcx_supdate = 239;
    int opcx_rc = 237;
    int opcx_aswizzle = 240;
    int opcx_aswrange = 241;
    int opcx_putfield_nowb = 204;
    int opcx_putstatic_nowb = 205;
    String[] opcNames = new String[]{"nop", "aconst_null", "iconst_m1", "iconst_0", "iconst_1", "iconst_2", "iconst_3", "iconst_4", "iconst_5", "lconst_0", "lconst_1", "fconst_0", "fconst_1", "fconst_2", "dconst_0", "dconst_1", "bipush", "sipush", "ldc", "ldc_w", "ldc2_w", "iload", "lload", "fload", "dload", "aload", "iload_0", "iload_1", "iload_2", "iload_3", "lload_0", "lload_1", "lload_2", "lload_3", "fload_0", "fload_1", "fload_2", "fload_3", "dload_0", "dload_1", "dload_2", "dload_3", "aload_0", "aload_1", "aload_2", "aload_3", "iaload", "laload", "faload", "daload", "aaload", "baload", "caload", "saload", "istore", "lstore", "fstore", "dstore", "astore", "istore_0", "istore_1", "istore_2", "istore_3", "lstore_0", "lstore_1", "lstore_2", "lstore_3", "fstore_0", "fstore_1", "fstore_2", "fstore_3", "dstore_0", "dstore_1", "dstore_2", "dstore_3", "astore_0", "astore_1", "astore_2", "astore_3", "iastore", "lastore", "fastore", "dastore", "aastore", "bastore", "castore", "sastore", "pop", "pop2", "dup", "dup_x1", "dup_x2", "dup2", "dup2_x1", "dup2_x2", "swap", "iadd", "ladd", "fadd", "dadd", "isub", "lsub", "fsub", "dsub", "imul", "lmul", "fmul", "dmul", "idiv", "ldiv", "fdiv", "ddiv", "irem", "lrem", "frem", "drem", "ineg", "lneg", "fneg", "dneg", "ishl", "lshl", "ishr", "lshr", "iushr", "lushr", "iand", "land", "ior", "lor", "ixor", "lxor", "iinc", "i2l", "i2f", "i2d", "l2i", "l2f", "l2d", "f2i", "f2l", "f2d", "d2i", "d2l", "d2f", "i2b", "i2c", "i2s", "lcmp", "fcmpl", "fcmpg", "dcmpl", "dcmpg", "ifeq", "ifne", "iflt", "ifge", "ifgt", "ifle", "if_icmpeq", "if_icmpne", "if_icmplt", "if_icmpge", "if_icmpgt", "if_icmple", "if_acmpeq", "if_acmpne", "goto", "jsr", "ret", "tableswitch", "lookupswitch", "ireturn", "lreturn", "freturn", "dreturn", "areturn", "return", "getstatic", "putstatic", "getfield", "putfield", "invokevirtual", "invokespecial", "invokestatic", "invokeinterface", "xxxunusedxxx", "new", "newarray", "anewarray", "arraylength", "athrow", "checkcast", "instanceof", "monitorenter", "monitorexit", "wide", "multianewarray", "ifnull", "ifnonnull", "goto_w", "jsr_w", "breakpoint", "203", "putfield_nowb", "putstatic_nowb", "206", "207", "208", "209", "210", "211", "212", "213", "214", "215", "216", "217", "218", "219", "220", "221", "222", "223", "224", "225", "226", "227", "228", "229", "230", "231", "232", "233", "234", "235", "236", "rc", "aupdate", "supdate", "aswizzle", "aswrange", "242", "243", "244", "245", "246", "247", "248", "249", "250", "251", "252", "253", "254", "255"};
    byte VARIABLE = -1;
    byte[] opcSize = new byte[]{1, 1, 1, 1, 1, 1, 1, 1, 1, 1, 1, 1, 1, 1, 1, 1, 2, 3, 2, 3, 3, 2, 2, 2, 2, 2, 1, 1, 1, 1, 1, 1, 1, 1, 1, 1, 1, 1, 1, 1, 1, 1, 1, 1, 1, 1, 1, 1, 1, 1, 1, 1, 1, 1, 2, 2, 2, 2, 2, 1, 1, 1, 1, 1, 1, 1, 1, 1, 1, 1, 1, 1, 1, 1, 1, 1, 1, 1, 1, 1, 1, 1, 1, 1, 1, 1, 1, 1, 1, 1, 1, 1, 1, 1, 1, 1, 1, 1, 1, 1, 1, 1, 1, 1, 1, 1, 1, 1, 1, 1, 1, 1, 1, 1, 1, 1, 1, 1, 1, 1, 1, 1, 1, 1, 1, 1, 1, 1, 1, 1, 1, 1, 3, 1, 1, 1, 1, 1, 1, 1, 1, 1, 1, 1, 1, 1, 1, 1, 1, 1, 1, 1, 1, 3, 3, 3, 3, 3, 3, 3, 3, 3, 3, 3, 3, 3, 3, 3, 3, 2, -1, -1, 1, 1, 1, 1, 1, 1, 3, 3, 3, 3, 3, 3, 3, 5, 1, 3, 2, 3, 1, 1, 3, 3, 1, 1, -1, 4, 3, 3, 5, 5, 1, 1, 3, 3, 1, 1, 1, 1, 1, 1, 1, 1, 1, 1, 1, 1, 1, 1, 1, 1, 1, 1, 1, 1, 1, 1, 1, 1, 1, 1, 1, 1, 1, 1, 1, 2, 2, 2, 1, 1, 1, 1, 1, 1, 1, 1, 1, 1, 1, 1, 1, 1, 1, 1};
    int[] opcXMap = new int[]{0, 18, 18, 18, 18, 18, 18, 18, 18, 18, 18, 18, 18, 18, 18, 18, 18, 18, 18, 18, 18, 21, 22, 23, 24, 25, 21, 21, 21, 21, 22, 22, 22, 22, 23, 23, 23, 23, 24, 24, 24, 24, 25, 25, 25, 25, 46, 47, 48, 49, 50, 51, 52, 53, 54, 55, 56, 57, 58, 54, 54, 54, 54, 55, 55, 55, 55, 56, 56, 56, 56, 57, 57, 57, 57, 58, 58, 58, 58, 79, 80, 81, 82, 83, 84, 85, 86, 87, 88, 89, 90, 91, 92, 93, 94, 95, 96, 97, 98, 99, 100, 101, 102, 103, 104, 105, 106, 107, 108, 109, 110, 111, 112, 113, 114, 115, 116, 117, 118, 119, 120, 121, 122, 123, 124, 125, 126, 127, 128, 129, 130, 131, 132, 133, 134, 135, 136, 137, 138, 139, 140, 141, 142, 143, 144, 145, 146, 147, 148, 149, 150, 151, 152, 153, 154, 155, 156, 157, 158, 159, 160, 161, 162, 163, 164, 165, 166, 167, 168, 169, 170, 170, 172, 173, 174, 175, 176, 177, 178, 179, 180, 181, 182, 183, 184, 185, 0, 187, 188, 188, 190, 191, 192, 193, 194, 195, 0, 197, 198, 199, 167, 168, 0, 0, 204, 205, 0, 0, 0, 0, 0, 0, 0, 0, 0, 0, 0, 0, 0, 0, 0, 0, 0, 0, 0, 0, 0, 0, 0, 0, 0, 0, 0, 0, 0, 0, 0, 237, 238, 239, 240, 241, 0, 0, 0, 0, 0, 0, 0, 0, 0, 0, 0, 0, 0, 0};
}
